CHANGES.rst
LICENSE
MANIFEST.in
README.rst
arrr.py
setup.py
arrr1.egg-info/PKG-INFO
arrr1.egg-info/SOURCES.txt
arrr1.egg-info/dependency_links.txt
arrr1.egg-info/entry_points.txt
arrr1.egg-info/top_level.txt