Metadata-Version: 1.1
Name: arrr1
Version: 1.0.1
Summary: A module and command to turn English into Pirate speak.
Home-page: https://github.com/luqmaanb/arrr1
Author: Nicholas H.Tollervey
Author-email: luqmaanbaboo@gmail.com
License: MIT
Platform: UNKNOWN
Classifier: Development Status :: 5 - Production/Stable
Classifier: Environment :: Console
Classifier: Intended Audience :: Developers
Classifier: Intended Audience :: Education
Classifier: License :: OSI Approved :: MIT License
Classifier: Natural Language :: English
Classifier: Programming Language :: Python :: 3.5
Classifier: Topic :: Education
Classifier: Topic :: Communications
Classifier: Topic :: Software Development :: Internationalization
